<?xml version="1.0" ?>
<ROW>
	<ID_PERSON>173</ID_PERSON>
	<Given_Name>Sebastiano</Given_Name>
	<Surname>Giustinian</Surname>
	<Titles>
		<Title>
			<aat>300230874</aat>
			<ita>Cavaliere</ita>
			<eng>Knight</eng>
		</Title>
	</Titles>
	<Patronymic>
		<eng>Marino</eng>
	</Patronymic>
	<Occupation>
		<aat>300236547</aat>
		<ita>Nobiluomo</ita>
		<eng>Nobleman</eng>
	</Occupation>
	<Activities>
		<Activity>
			<aat>300236171</aat>
			<ita>Capitano</ita>
			<eng>Captain</eng>
		</Activity>
	</Activities>
	<Place_of_birth>3164603</Place_of_birth>
	<Place_of_death/>
	<Work_locations>
		<Work_location>3164603</Work_location>
	</Work_locations>
	<Birth_Date_Earliest>1459</Birth_Date_Earliest>
	<Death_Date_Latest>1543-03-13</Death_Date_Latest>
	<Marriage_Date/>
	<Will_Date/>
	<Century>16th cent.</Century>
	<Fraction_Century/>
	<Events>
		<Event>
			<ID_EVENT>150</ID_EVENT>
			<Role>Recovered person</Role>
		</Event>
	</Events>
	<Sources/>
</ROW>
