<?xml version="1.0" ?>
<ROW>
	<ID_EVENT>164</ID_EVENT>
	<Name_Event>Francesco Lazzaroni together with other Venetians noblemen mediates between the Lateran Canons of Carità and the Camaldolese monks of Monte Rua for the island's sale</Name_Event>
	<Typology>Social</Typology>
	<Subtypology>Religious order's transfer</Subtypology>
	<Synopsis/>
	<Century>17th cent.</Century>
	<Fraction_century fraction_id="4060">Mid-century (40-60)</Fraction_century>
	<Date_Earliest>1644-01-01T00:00:00</Date_Earliest>
	<Island>3168468</Island>
	<People>
		<Person>
			<ID_PERSON>178</ID_PERSON>
			<Role>Mediator</Role>
		</Person>
		<Person>
			<ID_PERSON>182</ID_PERSON>
			<Role>Mediator</Role>
		</Person>
		<Person>
			<ID_PERSON>183</ID_PERSON>
			<Role>Mediator</Role>
		</Person>
		<Person>
			<ID_PERSON>181</ID_PERSON>
			<Role>Mediator</Role>
		</Person>
		<Person>
			<ID_PERSON>189</ID_PERSON>
			<Role>Mediator</Role>
		</Person>
		<Person>
			<ID_PERSON>184</ID_PERSON>
			<Role>Potential buyers</Role>
		</Person>
		<Person>
			<ID_PERSON>102</ID_PERSON>
			<Role>Potential sellers</Role>
		</Person>
	</People>
	<Bibliographic_Items>
		<Bibliographic_Item>
			<ID_BIBLIOGRAPHY>Bibl0018</ID_BIBLIOGRAPHY>
			<Date>1934</Date>
			<Pages>pp. 29-30</Pages>
		</Bibliographic_Item>
	</Bibliographic_Items>
	<Places/>
	<Sources>
		<Source>
			<ID_SOURCE>161</ID_SOURCE>
			<Event>Francesco Lazzaroni together with other Venetians noblemen mediates between the Lateran Canons of Carità and the Camaldolese monks of Monte Rua for the island's sale</Event>
		</Source>
	</Sources>
</ROW>
